[
	{
		"pkg": "@capacitor-community/barcode-scanner",
		"classpath": "com.dutchconcepts.capacitor.barcodescanner.BarcodeScanner"
	},
	{
		"pkg": "@capacitor/app",
		"classpath": "com.capacitorjs.plugins.app.AppPlugin"
	},
	{
		"pkg": "@capacitor/clipboard",
		"classpath": "com.capacitorjs.plugins.clipboard.ClipboardPlugin"
	},
	{
		"pkg": "@capacitor/dialog",
		"classpath": "com.capacitorjs.plugins.dialog.DialogPlugin"
	},
	{
		"pkg": "@capacitor/geolocation",
		"classpath": "com.capacitorjs.plugins.geolocation.GeolocationPlugin"
	},
	{
		"pkg": "@capacitor/status-bar",
		"classpath": "com.capacitorjs.plugins.statusbar.StatusBarPlugin"
	},
	{
		"pkg": "capacitor-native-biometric",
		"classpath": "com.epicshaggy.biometric.NativeBiometric"
	}
]
